{
  "translations": {
    "SIGN": {
      "IN_BUTTON": "Sign In",
      "IN_HEAD": "The portal MobiMed.ru for you and your family",
      "IN_TEXT": "The MobiMed.ru portal is the latest web service for those who value their health and time, takes care of their loved ones. Using MobiMed.ru you can safely and effectively manage your medical records, sign up for consultations and treatment and diagnostic events for themselves and family members from any geographic location with Internet access. ",
      "IN_ERRORS": "Something is wrong with your username or password :(",
      "IN_FOGOT_PASS": "Forgot your password?",
      "UP_BUTTON": "Sing Up",
      "UP_EMPTY_EMAIL": "Enter email",
      "UP_NOT_VALID_EMAIL": "Invalid email",
      "UP_EMPTY_PASS": "Enter Password",
      "UP_NOT_VALID_PASS": "Password must contain at least one number, at least one latin letter in lower and upper case and must be at least 7 characters long",
      "UP_NOT_MATCH_PASS": "Passwords do not match",
      "UP_CONFIRM_CODE": "Registration confirmation code",
      "UP_SUBMIT_CONFIRM": "Confirm",
      "UP_OK": "Successful registration",
      "UP_WRONG_LOG_OR_PASS": "The combination of Email or password is incorrect",
      "UP_EMAIL_ALREADY_REG": "This email is already registered",
      "UP_AGEEMENT": "I accept the terms of the agreement",
      "UP_BUTTON_SUBMIT": "Create Account",
      "UP_TITLE_LIC_AGR": "License Agreement",
      "UP_MAY_LOGIN": "The combination of Email or Password matches, you can Sing In",
      "CH_PASS_BUTTON": "Change Password",
      "CH_CONFIRM_CODE": "Password change confirmation code",
      "CH_CONFIRM_CODE_SENT": "A code to confirm the password has been sent by email",
      "CH_PASS_OK": "Successful password change",
      "CH_PASS_ACCOUNT_NOT_FOUND": "Such email or login does not exist",
      "CH_BUTTON_SUBMIT": "Change Password"
    },
    "HEADER": {
      "MESSAGES": "Messages",
      "CONT_NEW_MSS": "{{unreadCount}} New"
    },
    "MAINMENU": {
      "EVENTS": "My Events",
      "INVOICES": "Invoices",
      "MED_CARD": "Medical Record",
      "APPOINTMENT": "Make an Visit",
      "SIGNOUT": "Sing Out",
      "PROFILE": "Change personal data"
    },
    "HOME": {
      "BRANCH1": "Something bothering you?",
      "COLD": "Cold",
      "SICKCHILD": "Sick child",
      "HEADACHE": "Headache",
      "BRANCH2": "Sign up to a specialist",
      "BRANCH3": "Now Online",
      "BRANCH4": "Upcoming Events",
      "BRANCH5": "Promotions",
      "START_CHAT": "Start Chat",
      "MAKE_APPOINTMENT": "Make an appointment"
    },
    "VISIT": {
      "ONLINE": "Online",
      "FAVS": "Favorites",
      "FROM": "From",
      "CONSULT": "Consultation",
      "APPOINTMENTS": "Appointments",
      "ALERT_OK": "You are making an appointment",
      "CONFIRM_CANCEL": "Are you sure you want to cancel the appointment?"
    },
    "EVENTS_VISITS": {
      "FILTER_FUTURE": "Future Visits",
      "VISIT_CANCELED": "The appointment has been canceled.",
      "TITLE_ONLINE_CONF": "Online consultation",
      "TITLE_VISIT_CANCELED": "Canceled visit",
      "TITLE_VISIT": "Visit"
    },
    "INVOICES": {
      "INVOICE_NO": "Invoice #",
      "FILTER_UNPAID": "Unpaid",
      "FILTER_PAID": "Paid",
      "FILTER_ALL": "All",
      "QUANTITY": "Quantity",
      "COST": "Service cost",
      "TO_PAY": "To pay",
      "BILL_PAYMENT": "Bill Payment"
    },
    "MMK": {
      "APPOINTMENT": "Appointment",
      "RESULTS": "Results",
      "NO_MMK_RECORDS": "No entries"
    },
    "COMPONENT": {
      "DATAILS": "Details",
      "CLINICS": "Clinics",
      "SPECS": "Specialization",
      "SPEC_OR_DOCNAME": "Specialty or Name",
      "APPOINTMENT_DATE": "Appointment date",
      "BIRTH_DATE": "Date of Birth",
      "ARIA_DATE_LABEL": "Choose a Date",

      "FORM_LOGIN": "Email",
      "FORM_PASS": "Password",
      "FORM_REPASS": "Retype Password",

      "FORM_NAME": "First Name",
      "FORM_LAST_NAME": "Last Name",
      "FORM_MIDLE_NAME": "Middle Name",
      "FORM_TEL": "Phone",
      "FORM_GENDER": "Gender",
      "FORM_GENDER_M": "Male",
      "FORM_GENDER_F": "Female",
      "BUTTON_SAVE": "Save",
      "DATA_SAVED": "Data Saved",

      "FORM_VISIT_KIND": "Types of Reception",
      "FORM_VISIT_KIND_PRICE": "Cost",
      "FORM_VISIT_KIND_DURATION": "Duration",
      "BUT_MAKE_APPONTMENT": "Make an appointment",
      "BUT_CLOSE": "Close",
      "BUT_CONFIRM": "Yes",
      "BUT_CANCEL": "Cancel",
      "BUT_UPDATE": "Update",

      "NOT_VALID_NAME": "Enter a name",
      "NOT_VALID_LAST_NAME": "Enter last name",
      "NOT_VALID_BIRTHDAY": "Enter date of birth",
      "NOT_VALID_MMKID": "Please choose a name",

      "BROWSER_NOT_SUUPORT_FRAMES": "Your browser does not support inline frames!"
    },
    "EMPTY_DATA": {
      "NO_SLOTS": "There are no slots at the moment, select a different date",
      "NO_DOCTORS": "No specialists. Change request parameters",
      "NO_DOCTORS_CURRENTLY": "There are currently no specialists",
      "NO_EVENTS": "There are no events at this time",
      "NO_INVOICES": "No Invoices at this time",
      "NO_PROMO": "There are currently no promotions"
    },

    "BOTTOM": {
      "COPY": "© Post Modern Technology 2020. All rights reserved."
    }
  }
}
